intorods/__init__.py
intorods/intorods.py
intorods/filesys/__init__.py
intorods/filesys/fs_base.py
intorods/filesys/fs_ftp.py
intorods/filesys/fs_irods.py
intorods/filesys/fs_local.py
intorods/filesys/fs_scp.py
intorods/filesys/fs_sftp.py
intorods/filesys/fs_smb.py
intorods/filesys/loghandlers.py
intorods/filesys/sync.py
intorods/filesys/yml_filter.py
intorods/uxhash/hash.py
intorods-0.0.16.dist-info/licenses/LICENSE
intorods-0.0.16.dist-info/METADATA
intorods-0.0.16.dist-info/WHEEL
intorods-0.0.16.dist-info/entry_points.txt
intorods-0.0.16.dist-info/top_level.txt
intorods-0.0.16.dist-info/RECORD
