Metadata-Version: 2.4
Name: intorods
Version: 0.0.16
Summary: Tool to sync data to irods from various sources
Author-email: Erwin van Wieringen <erwin.van.wieringen@rivm.nl>, Robert Verhagen <robert.verhagen@rivm.nl>, Jan-Erek Thiede <jan.erek.thiede@rivm.nl>
Project-URL: Homepage, https://github.com/rivm-syso/intorods
Project-URL: Bug Tracker, https://github.com/rivm-syso/intorods/issues
Classifier: Programming Language :: Python :: 3
Requires-Python: >=3.7
License-File: LICENSE
Requires-Dist: cryptography
Requires-Dist: ftputil
Requires-Dist: paramiko
Requires-Dist: python-irodsclient
Requires-Dist: pyyaml
Requires-Dist: pysmb
Requires-Dist: jsonschema
Dynamic: license-file
